mx_platform_python/__init__.py
mx_platform_python/api_client.py
mx_platform_python/api_response.py
mx_platform_python/configuration.py
mx_platform_python/exceptions.py
mx_platform_python/py.typed
mx_platform_python/rest.py
mx_platform_python/api/__init__.py
mx_platform_python/api/accounts_api.py
mx_platform_python/api/ach_return_api.py
mx_platform_python/api/budgets_api.py
mx_platform_python/api/categories_api.py
mx_platform_python/api/goals_api.py
mx_platform_python/api/insights_api.py
mx_platform_python/api/institutions_api.py
mx_platform_python/api/investment_holdings_api.py
mx_platform_python/api/managed_data_api.py
mx_platform_python/api/members_api.py
mx_platform_python/api/merchants_api.py
mx_platform_python/api/microdeposits_api.py
mx_platform_python/api/monthly_cash_flow_profile_api.py
mx_platform_python/api/notifications_api.py
mx_platform_python/api/processor_token_api.py
mx_platform_python/api/rewards_api.py
mx_platform_python/api/spending_plan_api.py
mx_platform_python/api/statements_api.py
mx_platform_python/api/taggings_api.py
mx_platform_python/api/tags_api.py
mx_platform_python/api/transaction_rules_api.py
mx_platform_python/api/transactions_api.py
mx_platform_python/api/users_api.py
mx_platform_python/api/verifiable_credentials_api.py
mx_platform_python/api/widgets_api.py
mx_platform_python/models/__init__.py
mx_platform_python/models/account_create_request.py
mx_platform_python/models/account_create_request_body.py
mx_platform_python/models/account_number_response.py
mx_platform_python/models/account_numbers_response_body.py
mx_platform_python/models/account_owner_response.py
mx_platform_python/models/account_owners_response_body.py
mx_platform_python/models/account_response.py
mx_platform_python/models/account_response_body.py
mx_platform_python/models/account_update_request.py
mx_platform_python/models/account_update_request_body.py
mx_platform_python/models/accounts_response_body.py
mx_platform_python/models/ach_response.py
mx_platform_python-1.12.0.dist-info/licenses/LICENSE
mx_platform_python-1.12.0.dist-info/METADATA
mx_platform_python-1.12.0.dist-info/WHEEL
mx_platform_python-1.12.0.dist-info/top_level.txt
mx_platform_python-1.12.0.dist-info/RECORD
