Metadata-Version: 2.4
Name: mx-platform-python
Version: 1.12.0
Summary: MX Platform API
Home-page: https://pypi.org/project/mx-platform-python
Author: MX Platform API
Author-email: team@openapitools.org
Keywords: OpenAPI,OpenAPI-Generator,MX Platform API
License-File: LICENSE
Requires-Dist: urllib3<2.1.0,>=1.25.3
Requires-Dist: python-dateutil
Requires-Dist: pydantic<2,>=1.10.5
Requires-Dist: aenum
Dynamic: author
Dynamic: author-email
Dynamic: description
Dynamic: description-content-type
Dynamic: home-page
Dynamic: keywords
Dynamic: license-file
Dynamic: requires-dist
Dynamic: summary
